src/__init__.py
src/async_upload.py
src/sync_upload.py
tests/__init__.py
sync_and_asyncfile_uploading_JohnPractice-1.0.0.dist-info/LICENSE
sync_and_asyncfile_uploading_JohnPractice-1.0.0.dist-info/METADATA
sync_and_asyncfile_uploading_JohnPractice-1.0.0.dist-info/WHEEL
sync_and_asyncfile_uploading_JohnPractice-1.0.0.dist-info/top_level.txt
sync_and_asyncfile_uploading_JohnPractice-1.0.0.dist-info/RECORD
